balanced_loss/__init__.py
balanced_loss/losses.py
balanced_loss-0.1.1.dist-info/LICENSE
balanced_loss-0.1.1.dist-info/METADATA
balanced_loss-0.1.1.dist-info/WHEEL
balanced_loss-0.1.1.dist-info/top_level.txt
balanced_loss-0.1.1.dist-info/RECORD
