Metadata-Version: 2.1
Name: balanced-loss
Version: 0.1.1
Summary: Easy to use class-balanced cross-entropy and focal loss implementation for Pytorch.
Home-page: https://github.com/fcakyon/balanced-loss
Author: fcakyon
License: MIT
Keywords: machine-learning,deep-learning,ml,pytorch,vision,loss,image-classification,video-classification
Classifier: Development Status :: 5 - Production/Stable
Classifier: Operating System :: OS Independent
Classifier: Intended Audience :: Developers
Classifier: Intended Audience :: Science/Research
Classifier: Programming Language :: Python :: 3
Classifier: Programming Language :: Python :: 3.8
Classifier: Programming Language :: Python :: 3.9
Classifier: Programming Language :: Python :: 3.10
Classifier: Topic :: Software Development :: Libraries
Classifier: Topic :: Software Development :: Libraries :: Python Modules
Classifier: Topic :: Education
Classifier: Topic :: Scientific/Engineering
Classifier: Topic :: Scientific/Engineering :: Artificial Intelligence
Requires-Python: >=3.7
License-File: LICENSE
Requires-Dist: torch
Requires-Dist: numpy
Provides-Extra: tests
Requires-Dist: black==21.7b0; extra == "tests"
Requires-Dist: flake8==3.9.2; extra == "tests"
Requires-Dist: isort==5.9.2; extra == "tests"
Requires-Dist: click==8.0.4; extra == "tests"
Requires-Dist: importlib-metadata<4.3,>=1.1.0; python_version < "3.8" and extra == "tests"
Provides-Extra: dev
Requires-Dist: black==21.7b0; extra == "dev"
Requires-Dist: flake8==3.9.2; extra == "dev"
Requires-Dist: isort==5.9.2; extra == "dev"
Requires-Dist: click==8.0.4; extra == "dev"
Requires-Dist: importlib-metadata<4.3,>=1.1.0; python_version < "3.8" and extra == "dev"
